{"type":"object","properties":{"id":{"type":"number","format":"double"},"firstName":{"type":"string","format":""},"lastName":{"type":"string","format":""},"age":{"type":"number","format":"double"},"address":{"type":"object","properties":{"streetAddress":{"type":"string","format":""},"city":{"type":"string","format":""},"state":{"type":"string","format":""},"zipCode":{"type":"string","format":""}},"required":["streetAddress","city","state","zipCode"]},"phoneNumber":{"type":"array","items":{"type":"object","properties":{"number":{"type":"string","format":""}},"required":["number"]}}},"required":["id","firstName","lastName","age","address","phoneNumber"]}